{
	"name": "UPNetwork_PS_PSBZ_Point_table",
	"property_set_type_id": "排水泵站表格展示view",
	"is_base": 1,
	"properties": [{
		"name": "pipeCode",
		"alias": "管点编号",
		"sort": true
	}, {
		"name": "pipeNetworkType",
		"alias": "管网类型",
		"sort": true
	}, {
		"name": "tubeType",
		"alias": "管点类型",
		"sort": true
	}, {
		"name": "roadName",
		"alias": "所在道路",
		"sort": true
	}, {
		"name": "location",
		"alias": "位置",
		"sort": false
	}, {
		"name": "currentState",
		"alias": "当前状态",
		"sort": false,
		"convert": {
			"type": "dict",
			"data": "UPNetwork_currentState"
		}
	}, {
		"name": "ownershipUnit",
		"alias": "埋没日期",
		"sort": true,
		"convert": {
			"type": "date"
		}
	}, {
		"name": "unitConnectionWay",
		"alias": "权属单位",
		"sort": false,
		"convert": {
			"type": "dict",
			"data": "UPNetwork_ownershipUnits"
		}
	}],
	"create_date_time": 1568249792314,
	"update_date_time": 1568249792314
}